verox/__init__.py
verox/_about.py
verox/base.py
verox/client.py
verox/server.py
verox/ux.py
verox-0.0.11.dist-info/LICENSE
verox-0.0.11.dist-info/METADATA
verox-0.0.11.dist-info/WHEEL
verox-0.0.11.dist-info/top_level.txt
verox-0.0.11.dist-info/RECORD
