Metadata-Version: 2.1
Name: verox
Version: 0.0.11
Summary: An implementation of IPC using websockets.
Home-page: https://github.com/YodaPY/verox
Author: Yoda
Author-email: yodarlswitch@gmail.com
License: MIT
Platform: UNKNOWN
Classifier: Development Status :: 5 - Production/Stable
Classifier: Framework :: AsyncIO
Classifier: Intended Audience :: Developers
Classifier: Natural Language :: English
Classifier: Topic :: Software Development :: Libraries :: Python Modules
Classifier: Programming Language :: Python :: 3.8
Classifier: Programming Language :: Python :: 3.9
Classifier: Programming Language :: Python :: 3.10
Classifier: Programming Language :: Python :: Implementation :: CPython
Classifier: Programming Language :: Python :: 3 :: Only
Classifier: Topic :: Software Development :: Libraries
Classifier: Topic :: Software Development :: Libraries :: Application Frameworks
Classifier: Topic :: Software Development :: Libraries :: Python Modules
Requires-Python: >=3.8.0,<3.11
License-File: LICENSE
Requires-Dist: aiohttp (==3.8.1)
Requires-Dist: attrs (==21.2.0)
